napari_metroid/__init__.py
napari_metroid/_auto_mask.py
napari_metroid/_bssd.py
napari_metroid/_dock_widget.py
napari_metroid/_get_signals.py
napari_metroid/_mess.py
napari_metroid/_remove_bleaching.py
napari_metroid/_sample_data.py
napari_metroid/_widgets.py
napari_metroid/_writer.py
napari_metroid/napari.yaml
napari_metroid/_tests/__init__.py
napari_metroid/_tests/test_dock_widget.py
napari_metroid/_tests/test_sample_data.py
napari_metroid/_tests/test_writer.py
napari_metroid/_ui/metroid_main_widget.ui
napari_metroid/_ui/icons/auto_mask.png
napari_metroid/_ui/icons/bssd2.png
napari_metroid/_ui/icons/get_signals2.png
napari_metroid/_ui/icons/mess_icon.png
napari_metroid/_ui/icons/remove_photob.png
napari_metroid-0.0.5.dist-info/LICENSE
napari_metroid-0.0.5.dist-info/METADATA
napari_metroid-0.0.5.dist-info/WHEEL
napari_metroid-0.0.5.dist-info/entry_points.txt
napari_metroid-0.0.5.dist-info/top_level.txt
napari_metroid-0.0.5.dist-info/RECORD
