Metadata-Version: 2.1
Name: napari-metroid
Version: 0.0.5
Summary: This napari plugin creates several regions of interest of similar area over cells in a fluorescence video (2D+time). It then gets ROIs means over time and performs signal denoising: fixes photobleaching and separates signal from noise by means of blind source separation (with or without wavelet filtering).
Home-page: https://github.com/zoccoler/napari-metroid
Author: Marcelo Leomil Zoccoler
Author-email: marcelo.zoccoler@tu-dresden.de
License: BSD-3-Clause
Project-URL: Bug Tracker, https://github.com/zoccoler/napari-metroid/issues
Project-URL: Documentation, https://github.com/zoccoler/napari-metroid#README.md
Project-URL: Source Code, https://github.com/zoccoler/napari-metroid
Project-URL: User Support, https://github.com/zoccoler/napari-metroid/issues
Platform: UNKNOWN
Classifier: Development Status :: 2 - Pre-Alpha
Classifier: Intended Audience :: Developers
Classifier: Framework :: napari
Classifier: Topic :: Software Development :: Testing
Classifier: Programming Language :: Python
Classifier: Programming Language :: Python :: 3
Classifier: Programming Language :: Python :: 3.7
Classifier: Programming Language :: Python :: 3.8
Classifier: Operating System :: OS Independent
Classifier: License :: OSI Approved :: BSD License
Requires-Python: <3.9,>=3.7
License-File: LICENSE
Requires-Dist: numpy
Requires-Dist: scikit-learn
Requires-Dist: scikit-image
Requires-Dist: statsmodels
Requires-Dist: scipy
Requires-Dist: matplotlib
Requires-Dist: napari-skimage-regionprops (>=0.3.1)
